Metadata-Version: 1.0
Name: panda
Version: 0.1.4
Summary: A Python implementation of the Panda REST interface
Home-page: http://www.pandastream.com
Author: New Bamboo
Author-email: info@new-bamboo.co.uk
License: MIT
Keywords: panda rest video encoding stream service
Platform: UNKNOWN
Classifier: License :: OSI Approved :: MIT License
Classifier: Programming Language :: Python
Classifier: Development Status :: 4 - Beta
Classifier: Intended Audience :: Developers
Classifier: Topic :: Internet :: WWW/HTTP
